n2y/__init__.py
n2y/audit.py
n2y/blocks.py
n2y/comment.py
n2y/config.py
n2y/database.py
n2y/emoji.py
n2y/errors.py
n2y/export.py
n2y/file.py
n2y/logger.py
n2y/main.py
n2y/mentions.py
n2y/notion.py
n2y/notion_mocks.py
n2y/page.py
n2y/properties.py
n2y/property_values.py
n2y/rich_text.py
n2y/user.py
n2y/utils.py
n2y/data/mermaid_err.png
n2y/plugins/__init__.py
n2y/plugins/dbfootnotes.py
n2y/plugins/deepheaders.py
n2y/plugins/downloadfileproperty.py
n2y/plugins/expandbluetoggles.py
n2y/plugins/expandlinktopages.py
n2y/plugins/footnotes.py
n2y/plugins/jinjarenderpage.py
n2y/plugins/linkedheaders.py
n2y/plugins/mermaid.py
n2y/plugins/rawcodeblocks.py
n2y/plugins/removecallouts.py
n2y-0.10.2.dist-info/METADATA
n2y-0.10.2.dist-info/WHEEL
n2y-0.10.2.dist-info/entry_points.txt
n2y-0.10.2.dist-info/top_level.txt
n2y-0.10.2.dist-info/RECORD
